fygaro/webhook/__init__.py
fygaro/webhook/exceptions.py
fygaro/webhook/validator.py
fygaro_webhook-1.2.0.dist-info/licenses/LICENSE
fygaro_webhook-1.2.0.dist-info/METADATA
fygaro_webhook-1.2.0.dist-info/WHEEL
fygaro_webhook-1.2.0.dist-info/top_level.txt
fygaro_webhook-1.2.0.dist-info/RECORD
