Metadata-Version: 2.4
Name: fygaro-webhook
Version: 1.2.0
Summary: Webhook signature verification for Fygaro
Author-email: Fygaro <support@fygaro.com>
License: MIT License
Project-URL: Homepage, https://fygaro.com
Keywords: fygaro,webhook,signature
Classifier: Programming Language :: Python :: 3
Classifier: License :: OSI Approved :: MIT License
Classifier: Operating System :: OS Independent
Requires-Python: >=3.8
License-File: LICENSE
Dynamic: license-file
